kafka_connect_manager/__init__.py
kafka_connect_manager/__main__.py
kafka_connect_manager/cli.py
kafka_connect_manager/constants.py
kafka_connect_manager/main.py
kafka_connect_manager/utils.py
kafka_connect_manager-0.5.1.dist-info/entry_points.txt
kafka_connect_manager-0.5.1.dist-info/LICENSE
kafka_connect_manager-0.5.1.dist-info/WHEEL
kafka_connect_manager-0.5.1.dist-info/METADATA
kafka_connect_manager-0.5.1.dist-info/RECORD
