Metadata-Version: 2.1
Name: kafka-connect-manager
Version: 0.5.1
Summary: A tool to manage Apache Kafka Connect connectors and tasks using asyncio
Home-page: https://github.com/khan-ajamal/kafka-connect-manager
License: MIT
Keywords: kafka,kafka connect
Author: Ajamal Khan
Author-email: 13559558+khan-ajamal@users.noreply.github.com
Requires-Python: >=3.10,<4.0
Classifier: License :: OSI Approved :: MIT License
Classifier: Programming Language :: Python :: 3
Classifier: Programming Language :: Python :: 3.10
Classifier: Programming Language :: Python :: 3.11
Requires-Dist: httpx (>=0.23.0,<0.24.0)
Requires-Dist: typer[all] (>=0.6.1,<0.7.0)
Project-URL: Repository, https://github.com/khan-ajamal/kafka-connect-manager
